snippingtool/__init__.py
snippingtool/snippingTool.py
snippingtool-0.2.0.dist-info/licenses/LICENSE
snippingtool-0.2.0.dist-info/METADATA
snippingtool-0.2.0.dist-info/WHEEL
snippingtool-0.2.0.dist-info/top_level.txt
snippingtool-0.2.0.dist-info/RECORD
