Metadata-Version: 2.4
Name: snippingtool
Version: 0.2.0
Summary: A simple Python snipping tool using Tkinter and PIL
Home-page: https://github.com/rann-studio/snippingtool
Author: RannStudio
License: MIT
Project-URL: Source, https://github.com/rann-studio/snippingtool
Project-URL: Bug Tracker, https://github.com/rann-studio/snippingtool/issues
Classifier: Programming Language :: Python :: 3
Classifier: License :: OSI Approved :: MIT License
Classifier: Operating System :: Microsoft :: Windows
Classifier: Topic :: Multimedia :: Graphics :: Capture
Classifier: Intended Audience :: End Users/Desktop
Requires-Python: >=3.6
License-File: LICENSE
Requires-Dist: Pillow
Requires-Dist: pyautogui
Requires-Dist: pywin32
Dynamic: author
Dynamic: classifier
Dynamic: description
Dynamic: description-content-type
Dynamic: home-page
Dynamic: license
Dynamic: license-file
Dynamic: project-url
Dynamic: requires-dist
Dynamic: requires-python
Dynamic: summary
